byebyelogger/__init__.py
byebyelogger/logger.py
byebyelogger/core/__init__.py
byebyelogger/core/configuration.py
byebyelogger/core/stack_info.py
byebyelogger/style/__init__.py
byebyelogger/style/color.py
byebyelogger/style/format.py
ByeByeLogger-3.0.0.dist-info/METADATA
ByeByeLogger-3.0.0.dist-info/WHEEL
ByeByeLogger-3.0.0.dist-info/top_level.txt
ByeByeLogger-3.0.0.dist-info/RECORD
