Metadata-Version: 2.1
Name: ByeByeLogger
Version: 3.0.0
Summary: A simple, yet powerful Python logging library that makes you say goodbye to your standard logger.
Author: Aleksa Lukic
License: UNKNOWN
Platform: UNKNOWN
Classifier: License :: OSI Approved :: MIT License
Classifier: Operating System :: OS Independent
Classifier: Programming Language :: Python :: 3.7
Classifier: Programming Language :: Python :: 3.8
Classifier: Programming Language :: Python :: 3.9
Classifier: Programming Language :: Python :: 3.10
Classifier: Programming Language :: Python :: 3.11
Requires-Dist: colorama (==0.4.6)
